setup.py
opensearch/__init__.py
opensearch/client.py
opensearch/description.py
opensearch/osfeedparser.py
opensearch/query.py
opensearch/results.py
opensearch/url.py
opensearch.egg-info/PKG-INFO
opensearch.egg-info/SOURCES.txt
opensearch.egg-info/dependency_links.txt
opensearch.egg-info/top_level.txt
test/test_client.py
test/test_description.py
test/test_query.py
test/test_results.py