Metadata-Version: 1.0
Name: opensearch
Version: 0.9.2
Summary: Interact with opensearch services
Home-page: http://github.com/edsu/opensearch
Author: Ed Summers
Author-email: ehs@pobox.com
License: http://www.opensource.org/licenses/gpl-license.php
Platform: UNKNOWN
Classifier: Intended Audience :: Education
Classifier: Intended Audience :: Developers
Classifier: Intended Audience :: Information Technology
Classifier: License :: OSI Approved :: GNU General Public License (GPL)
Classifier: Programming Language :: Python
Classifier: Topic :: Text Processing :: General
